event_driven_app/__init__.py
event_driven_app/application.py
event_driven_app/entities.py
event_driven_app/services/__init__.py
event_driven_app/services/command_bus.py
event_driven_app/services/dependeny_injection.py
event_driven_app/services/service_manager.py
event_driven_app-0.1.4.dist-info/METADATA
event_driven_app-0.1.4.dist-info/WHEEL
event_driven_app-0.1.4.dist-info/RECORD
